_sam_module.cpython-38-darwin.so
samsum/__init__.py
samsum/__main__.py
samsum/_version.py
samsum/alignment_utils.py
samsum/args.py
samsum/classy.py
samsum/commands.py
samsum/file_parsers.py
samsum/logger.py
samsum/utilities.py
samsum/__pycache__/__init__.cpython-35-pytest-5.3.1.pyc
samsum/__pycache__/__init__.cpython-35.pyc
samsum/__pycache__/testing_utils.cpython-35.pyc
samsum-0.1.4.dist-info/LICENSE
samsum-0.1.4.dist-info/METADATA
samsum-0.1.4.dist-info/WHEEL
samsum-0.1.4.dist-info/entry_points.txt
samsum-0.1.4.dist-info/top_level.txt
samsum-0.1.4.dist-info/RECORD
