Metadata-Version: 2.1
Name: samsum
Version: 0.1.4
Summary: A light-weight python package for summarizing sequence coverage from SAM and BAM files
Home-page: https://github.com/hallamlab/samsum
Author: Connor Morgan-Lang, Matthew Tang, Ryan J. McLaughlin
Author-email: c.morganlang@gmail.com
License: GPL-3.0
Platform: UNKNOWN
Classifier: Environment :: Console
Classifier: Intended Audience :: Science/Research
Classifier: License :: OSI Approved :: GNU General Public License v3 (GPLv3)
Classifier: Natural Language :: English
Classifier: Operating System :: POSIX :: Linux
Classifier: Operating System :: MacOS :: MacOS X
Classifier: Programming Language :: C++
Classifier: Programming Language :: Python :: 3.6
Classifier: Programming Language :: Python :: 3.7
Classifier: Programming Language :: Python :: 3.8
Classifier: Topic :: Scientific/Engineering :: Bio-Informatics
Requires-Dist: numpy
Requires-Dist: pytest
Requires-Dist: pyfastx
